egraphics/__init__.py
egraphics/_cache.py
egraphics/_debug.py
egraphics/_egraphics.c
egraphics/_egraphics.cpython-314-x86_64-linux-musl.so
egraphics/_egraphics.pyi
egraphics/_g_buffer.py
egraphics/_g_buffer_view.py
egraphics/_g_buffer_view_map.py
egraphics/_image.py
egraphics/_render_target.py
egraphics/_shader.py
egraphics/_state.py
egraphics/_texture.py
egraphics/_texture_2d.py
egraphics/_weak_fifo_set.py
egraphics/py.typed
egraphics.libs/libGL-dc91beac.so.1.2.0
egraphics.libs/libGLU-c7223b8a.so.1.3.1
egraphics.libs/libLLVM-c283adc8.so.20.1
egraphics.libs/libSPIRV-Tools-0811532b.so
egraphics.libs/libX11-07308cf9.so.6.4.0
egraphics.libs/libX11-xcb-6ec0e870.so.1.0.0
egraphics.libs/libXau-d5d7809a.so.6.0.0
egraphics.libs/libXdmcp-a00f29b9.so.6.0.0
egraphics.libs/libXext-1d5f2c45.so.6.4.0
egraphics.libs/libXxf86vm-311af791.so.1.0.0
egraphics.libs/libbsd-97c20792.so.0.12.2
egraphics.libs/libdrm-df347371.so.2.124.0
egraphics.libs/libdrm_amdgpu-176a0b2f.so.1.124.0
egraphics.libs/libdrm_intel-d0544be2.so.1.124.0
egraphics.libs/libelf-0-bb481905.193.so
egraphics.libs/libexpat-e4f7ec7e.so.1.11.1
egraphics.libs/libffi-94bb0f57.so.8.1.4
egraphics.libs/libgallium-25-924d4c51.1.9.so
egraphics.libs/libgcc_s-0cd532bd.so.1
egraphics.libs/liblzma-9cee5efb.so.5.8.1
egraphics.libs/libmd-21fd7d29.so.0.1.0
egraphics.libs/libpciaccess-182239cd.so.0.11.1
egraphics.libs/libstdc++-5d72f927.so.6.0.33
egraphics.libs/libxcb-d7c721d4.so.1.1.0
egraphics.libs/libxcb-dri3-ee3c4091.so.0.1.0
egraphics.libs/libxcb-glx-7002376a.so.0.0.0
egraphics.libs/libxcb-present-cf43fc19.so.0.0.0
egraphics.libs/libxcb-randr-f1f612f1.so.0.1.0
egraphics.libs/libxcb-shm-00e22116.so.0.0.0
egraphics.libs/libxcb-sync-4df02f74.so.1.0.0
egraphics.libs/libxcb-xfixes-608bb6df.so.0.0.0
egraphics.libs/libxml2-88ee13e2.so.2.13.9
egraphics.libs/libxshmfence-0fa932a7.so.1.0.0
egraphics.libs/libzstd-f3c21b15.so.1.5.7
egraphics-0.27.0.dist-info/METADATA
egraphics-0.27.0.dist-info/WHEEL
egraphics-0.27.0.dist-info/RECORD
egraphics-0.27.0.dist-info/sboms/auditwheel.cdx.json
