Metadata-Version: 2.4
Name: egraphics
Version: 0.27.0
Summary: Graphics Library
Author: Erik Soma
Author-email: stillusingirc@gmail.com
Requires-Python: >=3.14
Classifier: Programming Language :: Python :: 3
Classifier: Programming Language :: Python :: 3.14
Requires-Dist: egeometry (>=0,<1)
Requires-Dist: emath (>=0,<1)
Requires-Dist: eplatform (>=0.20.1,<0.21.0)
Requires-Dist: pillow (>=10.4,<12)
